coco_dataset/__init__.py
coco_dataset/coco_dataset_download.py
coco_dataset/test.py
CocoDataset-0.1.2.dist-info/LICENSE.txt
CocoDataset-0.1.2.dist-info/METADATA
CocoDataset-0.1.2.dist-info/WHEEL
CocoDataset-0.1.2.dist-info/top_level.txt
CocoDataset-0.1.2.dist-info/RECORD
