Metadata-Version: 2.1
Name: CocoDataset
Version: 0.1.2
Summary: COCO Dataset Download
Home-page: https://github.com/falahgs/
Author: Falahgs.G.Saleih
Author-email: falahgs07@gmail.com
License: MIT
Keywords: Keras,Tensorflow,Classification,coco dataset
Platform: UNKNOWN
Classifier: Programming Language :: Python :: 3
Classifier: License :: OSI Approved :: MIT License
Classifier: Operating System :: OS Independent
Requires-Python: >=3.6
Requires-Dist: pycocotools
